README.txt
freearch.theme-configure.zcml
setup.py
docs/LICENSE.GPL
docs/LICENSE.txt
freearch/__init__.py
freearch.theme.egg-info/PKG-INFO
freearch.theme.egg-info/SOURCES.txt
freearch.theme.egg-info/dependency_links.txt
freearch.theme.egg-info/entry_points.txt
freearch.theme.egg-info/namespace_packages.txt
freearch.theme.egg-info/not-zip-safe
freearch.theme.egg-info/paster_plugins.txt
freearch.theme.egg-info/requires.txt
freearch.theme.egg-info/top_level.txt
freearch/theme/__init__.py
freearch/theme/configure.zcml
freearch/theme/profiles.zcml
freearch/theme/setuphandlers.py
freearch/theme/skins.zcml
freearch/theme/browser/__init__.py
freearch/theme/browser/configure.zcml
freearch/theme/browser/foldertitle.py
freearch/theme/browser/frontpage.py
freearch/theme/browser/interfaces.py
freearch/theme/browser/logo.py
freearch/theme/browser/path_bar.py
freearch/theme/browser/sections.py
freearch/theme/browser/siteactions.py
freearch/theme/browser/images/README.txt
freearch/theme/browser/images/accessibility-trans.png
freearch/theme/browser/images/contact-trans.png
freearch/theme/browser/images/es_box1_bg.png
freearch/theme/browser/images/es_box2_bg.png
freearch/theme/browser/images/es_box3_bg.png
freearch/theme/browser/images/es_ots_bg1.png
freearch/theme/browser/images/es_ots_bg2.png
freearch/theme/browser/images/es_ots_bg3.png
freearch/theme/browser/images/footer_bg.png
freearch/theme/browser/images/header.jpg
freearch/theme/browser/images/header_bg.png
freearch/theme/browser/images/leipis_bg.png
freearch/theme/browser/images/logo-trans.png
freearch/theme/browser/images/menu_bullet-trans.png
freearch/theme/browser/images/menu_erotinviiva.png
freearch/theme/browser/images/paaots_bg.png
freearch/theme/browser/images/pdf_kuvake.png
freearch/theme/browser/images/print-trans.png
freearch/theme/browser/images/shadow-left.png
freearch/theme/browser/images/shadow-right.png
freearch/theme/browser/images/sitemap-trans.png
freearch/theme/browser/images/sivupolku_bg.png
freearch/theme/browser/images/val_active_bg.png
freearch/theme/browser/images/val_bg.png
freearch/theme/browser/images/val_erotin.png
freearch/theme/browser/images/val_mouseover_bg.png
freearch/theme/browser/javascript/README.txt
freearch/theme/browser/stylesheets/IE6Fixes.css
freearch/theme/browser/stylesheets/IEFixes.css
freearch/theme/browser/stylesheets/README.txt
