Metadata-Version: 1.0
Name: freearch.theme
Version: 1.0.2
Summary: Free Arch Theme for Plone
Home-page: freearch
Author: Mikko Ohtamaa
Author-email: mikko@redinnovation.com
License: GPL
Keywords: web zope plone theme skin
Platform: UNKNOWN
Classifier: Framework :: Plone
Classifier: Framework :: Zope2
Classifier: Framework :: Zope3
Classifier: Programming Language :: Python
Classifier: Topic :: Software Development :: Libraries :: Python Modules
